{
  "items": [
    {
      "type": "file",
      "ctime": 1688790386956,
      "path": "Fleeting Notes.md"
    },
    {
      "type": "file",
      "ctime": 1699519475315,
      "path": "Top of My Mind.md"
    },
    {
      "type": "file",
      "ctime": 1688792975984,
      "path": "grove-home.md"
    },
    {
      "type": "file",
      "ctime": 1691570558131,
      "path": "private/tasks kanban.md"
    },
    {
      "type": "file",
      "ctime": 1691491839031,
      "path": "private/My Core Principles.md"
    },
    {
      "type": "file",
      "ctime": 1691565274445,
      "path": "private/Productivity.md",
      "title": "My Workflow"
    },
    {
      "type": "file",
      "ctime": 1690183755704,
      "path": "inbox/Books.md"
    },
    {
      "type": "file",
      "ctime": 1690242791351,
      "path": "ideas.md"
    },
    {
      "type": "file",
      "ctime": 1690615067491,
      "path": "doadp/dreams_of_a_dead_planet.md"
    },
    {
      "type": "file",
      "ctime": 1690615100801,
      "path": "thingamabob.md"
    },
    {
      "type": "file",
      "ctime": 1690615081926,
      "path": "Godot.md"
    },
    {
      "type": "file",
      "ctime": 1690615085807,
      "path": "Blender.md"
    },
    {
      "type": "file",
      "ctime": 1698219397522,
      "path": "inbox.md"
    },
    {
      "type": "file",
      "ctime": 1688879260924,
      "path": "Shortcuts.md"
    },
    {
      "type": "file",
      "ctime": 1690086849703,
      "path": "private/Getting my house in order.md"
    },
    {
      "type": "file",
      "ctime": 1691573453006,
      "path": "How Should I use Obsidian?.canvas"
    },
    {
      "type": "file",
      "ctime": 1688796811035,
      "path": "public/etc/meta/Markdown.md",
      "title": "Obsidian Markdown"
    },
    {
      "type": "file",
      "ctime": 1697622201743,
      "path": "private/Assets.md"
    },
    {
      "type": "file",
      "ctime": 1698219403184,
      "path": "private/Art-Scene-NSW.md"
    },
    {
      "type": "file",
      "ctime": 1698221282384,
      "path": "projects/drawabox.md"
    },
    {
      "type": "file",
      "ctime": 1699321568050,
      "path": "private/cool images.md"
    },
    {
      "type": "file",
      "ctime": 1699600341931,
      "path": "Olive-Art.md"
    },
    {
      "type": "file",
      "ctime": 1702276505300,
      "path": "private/Wishlist.md"
    },
    {
      "type": "file",
      "ctime": 1702278624142,
      "path": "private/Arts-Visual.md"
    },
    {
      "type": "file",
      "ctime": 1703121489741,
      "path": "computing.md"
    },
    {
      "type": "file",
      "ctime": 1704343063086,
      "path": "private/Really actually tidying my obsidian vault.md"
    },
    {
      "type": "file",
      "ctime": 1704343570733,
      "path": "private/web-sharing.md"
    },
    {
      "type": "file",
      "ctime": 1704497442254,
      "path": "private/About Me.md"
    }
  ]
}